{
    "skills": [
        {
            "name": "Java",
            "icon": "FaJava"
        },
        {
            "name": "Python",
            "icon": "FaPython"
        },
        {
            "name": "Node.js",
            "icon": "FaNodeJs"
        },
        {
            "name": "MySQL",
            "icon": "FaDatabase"
        },
        {
            "name": "Docker",
            "icon": "FaServer"
        },
        {
            "name": "Linux",
            "icon": "FaLinux"
        },
        {
            "name": "Git",
            "icon": "FaGitAlt"
        },
        {
            "name": "AWS",
            "icon": "FaCloud"
        }
    ],
    "education": [
        {
            "logo": "https://jntugv.edu.in/static/media/jntugvcev.b33bb43b07b2037ab043.jpg/",
            "degree": "B.Tech in Information Technology",
            "institution": "JNTU-GV College of Engineering, Vizianagaram (A)",
            "university": "Jawaharlal Nehru Technological University Gurajada Vizianagaram",
            "year": "2022 - 2025",
            "achievements": [
                "Developed scalable registration systems utilizing Node.js, Express, and MySQL.",
                "Acted as a Coordinator for the WebBlaze technical workshop.",
                "Membership chair for ACM Student Chapter, organizing technical cohorts."
            ]
        },
        {
            "logo": "/images/gptsklm.png",
            "degree": "Diploma in Computer Science & Engineering",
            "institution": "Government Polytechnic College, Srikakulam",
            "university": "State Board of Technical Education and Training",
            "year": "2019 - 2022",
            "achievements": [
                "Graduated with Distinction (85%).",
                "Built and maintained college digital portals for internal management.",
                "Skilled with Hardware and System Administration through Industry Exposure."
            ]
        }
    ],
    "hobbies": [
        "Exploring system design patterns",
        "Participating in technical hackathons",
        "Cybersecurity research",
        "Chess and Strategy Games"
    ]
}